vlm4ocr/__init__.py
vlm4ocr/assets/default_prompt_templates/ocr_HTML_system_prompt.txt
vlm4ocr/assets/default_prompt_templates/ocr_HTML_user_prompt.txt
vlm4ocr/assets/default_prompt_templates/ocr_JSON_system_prompt.txt
vlm4ocr/assets/default_prompt_templates/ocr_markdown_system_prompt.txt
vlm4ocr/assets/default_prompt_templates/ocr_markdown_user_prompt.txt
vlm4ocr/assets/default_prompt_templates/ocr_text_system_prompt.txt
vlm4ocr/assets/default_prompt_templates/ocr_text_user_prompt.txt
vlm4ocr/cli.py
vlm4ocr/data_types.py
vlm4ocr/ocr_engines.py
vlm4ocr/utils.py
vlm4ocr/vlm_engines.py
vlm4ocr-0.4.1.dist-info/METADATA
vlm4ocr-0.4.1.dist-info/WHEEL
vlm4ocr-0.4.1.dist-info/entry_points.txt
vlm4ocr-0.4.1.dist-info/RECORD
